tensorflow_asr/__init__.py
tensorflow_asr/callbacks.py
tensorflow_asr/configs.py
tensorflow_asr/datasets.py
tensorflow_asr/schemas.py
tensorflow_asr/tokenizers.py
tensorflow_asr/augmentations/__init__.py
tensorflow_asr/augmentations/augmentation.py
tensorflow_asr/augmentations/methods/__init__.py
tensorflow_asr/augmentations/methods/base_method.py
tensorflow_asr/augmentations/methods/gaussnoise.py
tensorflow_asr/augmentations/methods/specaugment.py
tensorflow_asr/features/__init__.py
tensorflow_asr/features/gammatone.py
tensorflow_asr/losses/__init__.py
tensorflow_asr/losses/base_loss.py
tensorflow_asr/losses/ctc_loss.py
tensorflow_asr/losses/rnnt_loss.py
tensorflow_asr/metrics/__init__.py
tensorflow_asr/metrics/error_rates.py
tensorflow_asr/models/__init__.py
tensorflow_asr/models/base_layer.py
tensorflow_asr/models/base_model.py
tensorflow_asr/models/activations/__init__.py
tensorflow_asr/models/activations/glu.py
tensorflow_asr/models/ctc/__init__.py
tensorflow_asr/models/ctc/base_ctc.py
tensorflow_asr/models/ctc/conformer.py
tensorflow_asr/models/ctc/deepspeech2.py
tensorflow_asr/models/ctc/jasper.py
tensorflow_asr/models/ctc/transformer.py
tensorflow_asr/models/decoders/__init__.py
tensorflow_asr/models/encoders/__init__.py
tensorflow_asr/models/encoders/conformer.py
tensorflow_asr/models/encoders/contextnet.py
tensorflow_asr/models/encoders/deepspeech2.py
tensorflow_asr/models/encoders/jasper.py
tensorflow_asr/models/encoders/rnnt.py
tensorflow_asr/models/encoders/transformer.py
tensorflow_asr/models/layers/__init__.py
tensorflow_asr/models/layers/blurpool.py
tensorflow_asr/models/layers/convolution.py
tensorflow_asr/models/layers/embedding.py
tensorflow_asr/models/layers/feature_extraction.py
tensorflow_asr/models/layers/memory.py
tensorflow_asr/models/layers/multihead_attention.py
tensorflow_asr/models/layers/positional_encoding.py
tensorflow_asr/models/layers/residual.py
tensorflow_asr/models/layers/sequence_wise_bn.py
TensorFlowASR-2.1.0.dist-info/LICENSE
TensorFlowASR-2.1.0.dist-info/METADATA
TensorFlowASR-2.1.0.dist-info/WHEEL
TensorFlowASR-2.1.0.dist-info/top_level.txt
TensorFlowASR-2.1.0.dist-info/RECORD
