Metadata-Version: 2.1
Name: TensorFlowASR
Version: 2.1.0
Summary: Almost State-of-the-art Automatic Speech Recognition using Tensorflow 2
Home-page: https://github.com/TensorSpeech/TensorFlowASR
Author: Huy Le Nguyen
Author-email: nlhuy.cs.16@gmail.com
Classifier: Programming Language :: Python :: 3.6
Classifier: Programming Language :: Python :: 3.7
Classifier: Programming Language :: Python :: 3.8
Classifier: Programming Language :: Python :: 3.9
Classifier: Intended Audience :: Science/Research
Classifier: Operating System :: POSIX :: Linux
Classifier: License :: OSI Approved :: Apache Software License
Classifier: Topic :: Software Development :: Libraries :: Python Modules
Requires-Python: >=3.6, <4
License-File: LICENSE
Requires-Dist: SoundFile ~=0.12.1
Requires-Dist: nltk ~=3.8.1
Requires-Dist: sentencepiece ~=0.1.99
Requires-Dist: tqdm ~=4.66.3
Requires-Dist: librosa ~=0.10.1
Requires-Dist: PyYAML ~=6.0.1
Requires-Dist: sounddevice ~=0.4.6
Requires-Dist: jinja2 ~=3.1.3
Requires-Dist: fire ~=0.5.0
Requires-Dist: jiwer ~=3.0.3
Provides-Extra: dev
Requires-Dist: pytest ~=7.4.1 ; extra == 'dev'
Requires-Dist: black ~=24.3.0 ; extra == 'dev'
Requires-Dist: pylint ~=3.2.1 ; extra == 'dev'
Requires-Dist: matplotlib ~=3.7.2 ; extra == 'dev'
Requires-Dist: pydot-ng ~=1.4.2 ; extra == 'dev'
Requires-Dist: graphviz ~=0.20.1 ; extra == 'dev'
Requires-Dist: pre-commit ~=3.7.0 ; extra == 'dev'
Requires-Dist: tf2onnx ~=1.16.1 ; extra == 'dev'
Requires-Dist: netron ~=7.6.8 ; extra == 'dev'
Provides-Extra: tf2-12
Requires-Dist: tensorflow ~=2.12.0 ; extra == 'tf2-12'
Requires-Dist: tensorflow-text ~=2.12.0 ; extra == 'tf2-12'
Provides-Extra: tf2-12-gpu
Requires-Dist: tensorflow[and-cuda] ~=2.12.0 ; extra == 'tf2-12-gpu'
Requires-Dist: tensorflow-text ~=2.12.0 ; extra == 'tf2-12-gpu'
Provides-Extra: tf2-13
Requires-Dist: tensorflow ~=2.13.0 ; extra == 'tf2-13'
Requires-Dist: tensorflow-text ~=2.13.0rc0 ; extra == 'tf2-13'
Provides-Extra: tf2-13-gpu
Requires-Dist: tensorflow[and-cuda] ~=2.13.0 ; extra == 'tf2-13-gpu'
Requires-Dist: tensorflow-text ~=2.13.0rc0 ; extra == 'tf2-13-gpu'
Provides-Extra: tf2-14
Requires-Dist: tensorflow ~=2.14.0 ; extra == 'tf2-14'
Requires-Dist: tensorflow-text ~=2.14.0 ; extra == 'tf2-14'
Provides-Extra: tf2-14-gpu
Requires-Dist: tensorflow[and-cuda] ~=2.14.0 ; extra == 'tf2-14-gpu'
Requires-Dist: tensorflow-text ~=2.14.0 ; extra == 'tf2-14-gpu'
Provides-Extra: tf2-15
Requires-Dist: tensorflow ~=2.15.0 ; extra == 'tf2-15'
Requires-Dist: tensorflow-text ~=2.15.0 ; extra == 'tf2-15'
Provides-Extra: tf2-15-gpu
Requires-Dist: tensorflow[and-cuda] ~=2.15.0 ; extra == 'tf2-15-gpu'
Requires-Dist: tensorflow-text ~=2.15.0 ; extra == 'tf2-15-gpu'
